gemmforge/VERSION
gemmforge/__init__.py
gemmforge/abstract_gemmlike_generator.py
gemmforge/abstract_generator.py
gemmforge/arch.py
gemmforge/common.py
gemmforge/csa_generator.py
gemmforge/exceptions.py
gemmforge/gemm_generator.py
gemmforge/interfaces.py
gemmforge/support.py
gemmforge/triad_generator.py
gemmforge/constructs/__init__.py
gemmforge/constructs/code.py
gemmforge/include/gemmgen_aux.cu
gemmforge/include/gemmgen_aux.h
gemmforge/initializers/__init__.py
gemmforge/initializers/abstract_initializer.py
gemmforge/initializers/initializers.py
gemmforge/loaders/__init__.py
gemmforge/loaders/abstract_loader.py
gemmforge/loaders/shr_mem_loaders.py
gemmforge/loaders/shr_transpose_mem_loaders.py
gemmforge/loaders/stub_shr_mem_loader.py
gemmforge/matrix/__init__.py
gemmforge/matrix/dense.py
gemmforge/matrix/sparse.py
gemmforge/share/cmake/GemmForgeConfig.cmake
gemmforge/share/cmake/GemmForgeConfigVersion.cmake
gemmforge-0.0.202.dist-info/AUTHORS
gemmforge-0.0.202.dist-info/LICENSE
gemmforge-0.0.202.dist-info/METADATA
gemmforge-0.0.202.dist-info/WHEEL
gemmforge-0.0.202.dist-info/top_level.txt
gemmforge-0.0.202.dist-info/RECORD
