Metadata-Version: 2.1
Name: gemmforge
Version: 0.0.202
Summary: GPU-GEMM generator
Home-page: https://github.com/ravil-mobile/gemmforge/wiki
Author: Ravil Dorozhinskii
Author-email: ravil.aviva.com@gmail.com
License: MIT
Platform: UNKNOWN
Classifier: Programming Language :: Python :: 3
Classifier: License :: OSI Approved :: MIT License
Classifier: Operating System :: OS Independent
Requires-Python: >=3.5
Requires-Dist: numpy
